pyln/grpc/__init__.py
pyln/grpc/node_pb2.py
pyln/grpc/node_pb2_grpc.py
pyln/grpc/primitives_pb2.py
pyln/grpc/py.typed
pyln_grpc_proto-24.2.1.dist-info/METADATA
pyln_grpc_proto-24.2.1.dist-info/WHEEL
pyln_grpc_proto-24.2.1.dist-info/RECORD
